README.rst
setup.py
restraint/__init__.py
restraint/exceptions.py
restraint/registry.py
restraint.egg-info/PKG-INFO
restraint.egg-info/SOURCES.txt
restraint.egg-info/dependency_links.txt
restraint.egg-info/requires.txt
restraint.egg-info/top_level.txt
restraint/restraints/__init__.py