Metadata-Version: 2.1
Name: restraint
Version: 0.0.1
Summary: Rate Limiting Module
Home-page: https://github.com/KyleJamesWalker/restraint-py
Author: Kyle James Walker
Author-email: KyleJamesWalker@gmail.com
License: MIT
Platform: UNKNOWN
Classifier: Development Status :: 1 - Planning
Classifier: Intended Audience :: Developers
Classifier: License :: OSI Approved :: MIT License
Classifier: Natural Language :: English
Classifier: Programming Language :: Python :: 3.6
Classifier: Programming Language :: Python :: 3.7
Classifier: Programming Language :: Python :: 3.8
Provides-Extra: package
Provides-Extra: test
Provides-Extra: setup
Provides-Extra: all
